contipay/__init__.py
contipay/core/__init__.py
contipay/core/client.py
contipay/helpers/__init__.py
contipay/helpers/payload.py
contipay/services/__init__.py
contipay/services/card.py
contipay/services/mobile.py
contipay-1.0.2.dist-info/METADATA
contipay-1.0.2.dist-info/WHEEL
contipay-1.0.2.dist-info/top_level.txt
contipay-1.0.2.dist-info/RECORD
