Metadata-Version: 2.4
Name: contipay
Version: 1.0.2
Summary: Official ContiPay Python SDK
Author-email: ContiPay <dereck.njani@contitouch.co.zw>
License: MIT
Keywords: payments,contitouch,contipay,sdk
Classifier: Programming Language :: Python :: 3
Classifier: License :: OSI Approved :: MIT License
Classifier: Operating System :: OS Independent
Requires-Python: >=3.8
Requires-Dist: requests>=2.25
